LICENSE
MANIFEST.in
README.md
requirements.txt
setup.py
llm/__init__.py
llm/main.py
llm/api/__init__.py
llm/api/anthropicapi.py
llm/api/openaiapi.py
llm/utils/__init__.py
llm/utils/apikeys.py
llm/utils/parsing.py
python_llm.egg-info/PKG-INFO
python_llm.egg-info/SOURCES.txt
python_llm.egg-info/dependency_links.txt
python_llm.egg-info/requires.txt
python_llm.egg-info/top_level.txt
tests/test_anthropic.py
tests/test_multi_stream.py
tests/test_openai.py