Metadata-Version: 2.1
Name: python-llm
Version: 0.2.0
Summary: An LLM wrapper for Humans
Home-page: https://github.com/danielgross/python-llm
Author: Daniel Gross
Author-email: d@dcgross.com
Requires-Python: >=3.6
License-File: LICENSE
